VisualContextualClassifier/VisualContextualClassifier.py
VisualContextualClassifier/__init__.py
visual_contextual_classifier-1.2.dist-info/METADATA
visual_contextual_classifier-1.2.dist-info/WHEEL
visual_contextual_classifier-1.2.dist-info/top_level.txt
visual_contextual_classifier-1.2.dist-info/RECORD
