Metadata-Version: 2.1
Name: visual-contextual-classifier
Version: 1.2
Summary: Predicts whether a sentence is a visual sentence or a contextual sentence
Home-page: https://github.com/jgore077/visual-contextual-classifier/blob/main/README.md
Author: James Gore
Author-email: james.gore@maine.edu
Requires-Dist: transformers >=4.44.2
Requires-Dist: torch >=2.4.1
Requires-Dist: requests >=2.32.3
Requires-Dist: tqdm >=4.66.5
